src/__init__.py
src/core.py
src/gui.py
src/win/cudart64_12.dll
src/win/gdcmCommon.dll
src/win/gdcmDICT.dll
src/win/gdcmDSED.dll
src/win/gdcmIOD.dll
src/win/gdcmMEXD.dll
src/win/gdcmMSFF.dll
src/win/gdcmcharls.dll
src/win/gdcmexpat.dll
src/win/gdcmgetopt.dll
src/win/gdcmjpeg12.dll
src/win/gdcmjpeg16.dll
src/win/gdcmjpeg8.dll
src/win/gdcmmd5.dll
src/win/gdcmopenjp2.dll
src/win/gdcmzlib.dll
src/win/pycrystal_core.cp39-win_amd64.pyd
src/win/zlib.dll
pystal-0.1.0.dist-info/LICENSE
pystal-0.1.0.dist-info/METADATA
pystal-0.1.0.dist-info/WHEEL
pystal-0.1.0.dist-info/entry_points.txt
pystal-0.1.0.dist-info/top_level.txt
pystal-0.1.0.dist-info/RECORD
